{
  "legislative_session": "2025RS",
  "identifier": "SR125",
  "title": "A RESOLUTION recognizing and honoring Senator Aaron Reed as the first Navy SEAL to serve in the Kentucky Senate.",
  "from_organization": "~{\"classification\": \"upper\"}",
  "classification": [
    "resolution"
  ],
  "subject": [
    "Commendations and Recognitions",
    "General Assembly",
    "Military Affairs and Civil Defense",
    "Veterans"
  ],
  "abstracts": [
    {
      "note": "Summary of Original Version",
      "abstract": "Recognize and honor Senator Aaron Reed as the first Navy SEAL to serve in the Kentucky Senate."
    }
  ],
  "other_titles": [],
  "other_identifiers": [],
  "actions": [
    {
      "description": "introduced in Senate",
      "date": "2025-03-04T05:00:00+00:00",
      "organization_id": "~{\"classification\": \"upper\"}",
      "classification": [
        "introduction"
      ],
      "related_entities": [],
      "_processing": {
        "log_file_created": "2025-10-24T23:24:25Z"
      }
    },
    {
      "description": "to Committee on Committees (S)",
      "date": "2025-03-04T05:00:00+00:00",
      "organization_id": "~{\"classification\": \"upper\"}",
      "classification": [
        "referral-committee"
      ],
      "related_entities": [],
      "_processing": {
        "log_file_created": "2025-10-24T23:24:25Z"
      }
    },
    {
      "description": "to Veterans, Military Affairs, & Public Protection (S)",
      "date": "2025-03-27T04:00:00+00:00",
      "organization_id": "~{\"classification\": \"upper\"}",
      "classification": [
        "referral-committee"
      ],
      "related_entities": [],
      "_processing": {
        "log_file_created": "2025-10-24T23:24:25Z"
      }
    }
  ],
  "sponsorships": [],
  "related_bills": [],
  "versions": [
    {
      "note": "Introduced",
      "links": [
        {
          "url": "https://apps.legislature.ky.gov/recorddocuments/bill/25RS/sr125/orig_bill.pdf",
          "media_type": "application/pdf"
        }
      ],
      "date": "",
      "classification": ""
    }
  ],
  "documents": [],
  "citations": [],
  "sources": [
    {
      "url": "https://apps.legislature.ky.gov/record/25RS/sr125.html",
      "note": ""
    }
  ],
  "extras": {
    "BDR": "1972"
  },
  "jurisdiction": {
    "id": "ocd-jurisdiction/country:us/state:ky/government",
    "name": "Kentucky",
    "classification": "state",
    "division_id": "ocd-division/country:us/state:ky"
  },
  "_processing": {
    "logs_latest_update": "2025-10-24T23:24:25Z"
  }
}