{
  "legislative_session": "2025RS",
  "identifier": "HB546",
  "title": "AN ACT relating to transportation, making an appropriation therefor, and declaring an emergency.",
  "from_organization": "~{\"classification\": \"lower\"}",
  "classification": [
    "bill"
  ],
  "subject": [
    "Budget and Financial Administration",
    "Cities",
    "Counties",
    "Highways, Streets, and Bridges",
    "Reports Mandated",
    "State Agencies"
  ],
  "abstracts": [
    {
      "note": "Summary of Original Version",
      "abstract": "Create new sections of KRS Chapter 176 to define terms relating to Local Assistance Road Program funding; require the Transportation Cabinet to establish procedures whereby cities and counties can submit projects for consideration in the Local Assistance Road Program; limit projects to those that are rehabilitative in nature and do not expand capacity or the design of the original road; limit state funding for any individual project to $500,000; require the cabinet to assign a score to each project evaluating the project's impact on safety, congestion, asset management, and cost; set deadlines for local government submission of projects and cabinet submission of projects with evaluative scores; establish a graduated local funding match requirement based on the county population ranking developed by the Cabinet for Economic Development under KRS 154.21-015; require the cabinet to report quarterly to the Legislative Research Commission on the activity relating to projects awarded grants; specify required elements of the report."
    }
  ],
  "other_titles": [],
  "other_identifiers": [],
  "actions": [
    {
      "description": "introduced in House",
      "date": "2025-02-14T05:00:00+00:00",
      "organization_id": "~{\"classification\": \"lower\"}",
      "classification": [
        "introduction"
      ],
      "related_entities": [],
      "_processing": {
        "log_file_created": "2025-10-24T23:24:27Z"
      }
    },
    {
      "description": "to Committee on Committees (H)",
      "date": "2025-02-14T05:00:00+00:00",
      "organization_id": "~{\"classification\": \"lower\"}",
      "classification": [
        "referral-committee"
      ],
      "related_entities": [],
      "_processing": {
        "log_file_created": "2025-10-24T23:24:27Z"
      }
    },
    {
      "description": "to Appropriations & Revenue (H)",
      "date": "2025-02-20T05:00:00+00:00",
      "organization_id": "~{\"classification\": \"lower\"}",
      "classification": [
        "referral-committee"
      ],
      "related_entities": [],
      "_processing": {
        "log_file_created": "2025-10-24T23:24:27Z"
      }
    },
    {
      "description": "reported favorably, 1st reading, to Calendar with Committee Substitute (1)",
      "date": "2025-02-25T05:00:00+00:00",
      "organization_id": "~{\"classification\": \"lower\"}",
      "classification": [
        "committee-passage"
      ],
      "related_entities": [],
      "_processing": {
        "log_file_created": "2025-10-24T23:24:27Z"
      }
    },
    {
      "description": "2nd reading, to Rules",
      "date": "2025-02-26T05:00:00+00:00",
      "organization_id": "~{\"classification\": \"lower\"}",
      "classification": [
        "reading-2"
      ],
      "related_entities": [],
      "_processing": {
        "log_file_created": "2025-10-24T23:24:27Z"
      }
    },
    {
      "description": "posted for passage in the Regular Orders of the Day for Thursday, February 27, 2025",
      "date": "2025-02-26T05:00:00+00:00",
      "organization_id": "~{\"classification\": \"lower\"}",
      "classification": [],
      "related_entities": [],
      "_processing": {
        "log_file_created": "2025-10-24T23:24:27Z"
      }
    },
    {
      "description": "3rd reading, passed 85-11 with Committee Substitute (1)",
      "date": "2025-02-27T05:00:00+00:00",
      "organization_id": "~{\"classification\": \"lower\"}",
      "classification": [
        "passage",
        "reading-3"
      ],
      "related_entities": [],
      "_processing": {
        "log_file_created": "2025-10-24T23:24:27Z"
      }
    },
    {
      "description": "received in Senate",
      "date": "2025-02-28T05:00:00+00:00",
      "organization_id": "~{\"classification\": \"upper\"}",
      "classification": [],
      "related_entities": [],
      "_processing": {
        "log_file_created": "2025-10-24T23:24:27Z"
      }
    },
    {
      "description": "to Committee on Committees (S)",
      "date": "2025-02-28T05:00:00+00:00",
      "organization_id": "~{\"classification\": \"upper\"}",
      "classification": [
        "referral-committee"
      ],
      "related_entities": [],
      "_processing": {
        "log_file_created": "2025-10-24T23:24:27Z"
      }
    },
    {
      "description": "to Transportation (S)",
      "date": "2025-03-04T05:00:00+00:00",
      "organization_id": "~{\"classification\": \"upper\"}",
      "classification": [
        "referral-committee"
      ],
      "related_entities": [],
      "_processing": {
        "log_file_created": "2025-10-24T23:24:27Z"
      }
    },
    {
      "description": "taken from Transportation (S)",
      "date": "2025-03-07T05:00:00+00:00",
      "organization_id": "~{\"classification\": \"upper\"}",
      "classification": [],
      "related_entities": [],
      "_processing": {
        "log_file_created": "2025-10-24T23:24:27Z"
      }
    },
    {
      "description": "1st reading",
      "date": "2025-03-07T05:00:00+00:00",
      "organization_id": "~{\"classification\": \"lower\"}",
      "classification": [
        "reading-1"
      ],
      "related_entities": [],
      "_processing": {
        "log_file_created": "2025-10-24T23:24:27Z"
      }
    },
    {
      "description": "returned to Transportation (S)",
      "date": "2025-03-07T05:00:00+00:00",
      "organization_id": "~{\"classification\": \"upper\"}",
      "classification": [],
      "related_entities": [],
      "_processing": {
        "log_file_created": "2025-10-24T23:24:27Z"
      }
    },
    {
      "description": "reported favorably, 2nd reading, to Rules with Committee Substitute (1) and Committee Amendment (1-title)",
      "date": "2025-03-11T04:00:00+00:00",
      "organization_id": "~{\"classification\": \"lower\"}",
      "classification": [
        "committee-passage"
      ],
      "related_entities": [],
      "_processing": {
        "log_file_created": "2025-10-24T23:24:27Z"
      }
    },
    {
      "description": "posted for passage in the Regular Orders of the Day for Wednesday, March 12, 2025",
      "date": "2025-03-11T04:00:00+00:00",
      "organization_id": "~{\"classification\": \"lower\"}",
      "classification": [],
      "related_entities": [],
      "_processing": {
        "log_file_created": "2025-10-24T23:24:27Z"
      }
    },
    {
      "description": "3rd reading, passed 37-0 with Committee Substitute (1) and  Committee Amendment (1-title)",
      "date": "2025-03-12T04:00:00+00:00",
      "organization_id": "~{\"classification\": \"lower\"}",
      "classification": [
        "passage",
        "reading-3"
      ],
      "related_entities": [],
      "_processing": {
        "log_file_created": "2025-10-24T23:24:27Z"
      }
    },
    {
      "description": "received in House",
      "date": "2025-03-12T04:00:00+00:00",
      "organization_id": "~{\"classification\": \"lower\"}",
      "classification": [],
      "related_entities": [],
      "_processing": {
        "log_file_created": "2025-10-24T23:24:27Z"
      }
    },
    {
      "description": "to Rules (H)",
      "date": "2025-03-12T04:00:00+00:00",
      "organization_id": "~{\"classification\": \"lower\"}",
      "classification": [
        "referral-committee"
      ],
      "related_entities": [],
      "_processing": {
        "log_file_created": "2025-10-24T23:24:27Z"
      }
    },
    {
      "description": "posted for passage for concurrence in Senate Committee Substitute (1) and   Committee Amendment (1-title)",
      "date": "2025-03-13T04:00:00+00:00",
      "organization_id": "~{\"classification\": \"lower\"}",
      "classification": [],
      "related_entities": [],
      "_processing": {
        "log_file_created": "2025-10-24T23:24:27Z"
      }
    },
    {
      "description": "House refused to concur in Senate Committee Substitute (1)",
      "date": "2025-03-14T04:00:00+00:00",
      "organization_id": "~{\"classification\": \"lower\"}",
      "classification": [],
      "related_entities": [],
      "_processing": {
        "log_file_created": "2025-10-24T23:24:27Z"
      }
    },
    {
      "description": "received in Senate",
      "date": "2025-03-14T04:00:00+00:00",
      "organization_id": "~{\"classification\": \"upper\"}",
      "classification": [],
      "related_entities": [],
      "_processing": {
        "log_file_created": "2025-10-24T23:24:27Z"
      }
    },
    {
      "description": "to Rules (S)",
      "date": "2025-03-14T04:00:00+00:00",
      "organization_id": "~{\"classification\": \"upper\"}",
      "classification": [
        "referral-committee"
      ],
      "related_entities": [],
      "_processing": {
        "log_file_created": "2025-10-24T23:24:27Z"
      }
    },
    {
      "description": "posted for passage for receding from Senate Committee Substitute (1) and Committee Amendment (1-title)",
      "date": "2025-03-14T04:00:00+00:00",
      "organization_id": "~{\"classification\": \"lower\"}",
      "classification": [],
      "related_entities": [],
      "_processing": {
        "log_file_created": "2025-10-24T23:24:27Z"
      }
    },
    {
      "description": "Senate refused to recede from Committee Substitute (1) and  Committee Amendment (1-title)",
      "date": "2025-03-14T04:00:00+00:00",
      "organization_id": "~{\"classification\": \"lower\"}",
      "classification": [],
      "related_entities": [],
      "_processing": {
        "log_file_created": "2025-10-24T23:24:27Z"
      }
    },
    {
      "description": "Conference Committee appointed in House and Senate",
      "date": "2025-03-14T04:00:00+00:00",
      "organization_id": "~{\"classification\": \"upper\"}",
      "classification": [],
      "related_entities": [],
      "_processing": {
        "log_file_created": "2025-10-24T23:24:27Z"
      }
    },
    {
      "description": "Conference Committee report filed in House and Senate",
      "date": "2025-03-14T04:00:00+00:00",
      "organization_id": "~{\"classification\": \"upper\"}",
      "classification": [],
      "related_entities": [],
      "_processing": {
        "log_file_created": "2025-10-24T23:24:27Z"
      }
    },
    {
      "description": "Conference Committee report adopted in House and Senate",
      "date": "2025-03-14T04:00:00+00:00",
      "organization_id": "~{\"classification\": \"upper\"}",
      "classification": [],
      "related_entities": [],
      "_processing": {
        "log_file_created": "2025-10-24T23:24:27Z"
      }
    },
    {
      "description": "Free Conference Committee appointed in House and Senate",
      "date": "2025-03-14T04:00:00+00:00",
      "organization_id": "~{\"classification\": \"upper\"}",
      "classification": [],
      "related_entities": [],
      "_processing": {
        "log_file_created": "2025-10-24T23:24:27Z"
      }
    },
    {
      "description": "Free Conference Committee report filed in House and Senate",
      "date": "2025-03-14T04:00:00+00:00",
      "organization_id": "~{\"classification\": \"upper\"}",
      "classification": [],
      "related_entities": [],
      "_processing": {
        "log_file_created": "2025-10-24T23:24:27Z"
      }
    },
    {
      "description": "Free Conference Committee report adopted in Senate",
      "date": "2025-03-14T04:00:00+00:00",
      "organization_id": "~{\"classification\": \"upper\"}",
      "classification": [],
      "related_entities": [],
      "_processing": {
        "log_file_created": "2025-10-24T23:24:27Z"
      }
    },
    {
      "description": "passed 34-0",
      "date": "2025-03-14T04:00:00+00:00",
      "organization_id": "~{\"classification\": \"lower\"}",
      "classification": [
        "passage"
      ],
      "related_entities": [],
      "_processing": {
        "log_file_created": "2025-10-24T23:24:27Z"
      }
    },
    {
      "description": "received in House",
      "date": "2025-03-14T04:00:00+00:00",
      "organization_id": "~{\"classification\": \"lower\"}",
      "classification": [],
      "related_entities": [],
      "_processing": {
        "log_file_created": "2025-10-24T23:24:27Z"
      }
    },
    {
      "description": "to Rules (H)",
      "date": "2025-03-14T04:00:00+00:00",
      "organization_id": "~{\"classification\": \"lower\"}",
      "classification": [
        "referral-committee"
      ],
      "related_entities": [],
      "_processing": {
        "log_file_created": "2025-10-24T23:24:27Z"
      }
    },
    {
      "description": "posted for passage for consideration of Free Conference Committee Report",
      "date": "2025-03-14T04:00:00+00:00",
      "organization_id": "~{\"classification\": \"lower\"}",
      "classification": [],
      "related_entities": [],
      "_processing": {
        "log_file_created": "2025-10-24T23:24:27Z"
      }
    },
    {
      "description": "Free Conference Committee report adopted in House",
      "date": "2025-03-14T04:00:00+00:00",
      "organization_id": "~{\"classification\": \"lower\"}",
      "classification": [],
      "related_entities": [],
      "_processing": {
        "log_file_created": "2025-10-24T23:24:27Z"
      }
    },
    {
      "description": "passed 74-6",
      "date": "2025-03-14T04:00:00+00:00",
      "organization_id": "~{\"classification\": \"lower\"}",
      "classification": [
        "passage"
      ],
      "related_entities": [],
      "_processing": {
        "log_file_created": "2025-10-24T23:24:27Z"
      }
    },
    {
      "description": "enrolled, signed by Speaker of the House",
      "date": "2025-03-14T04:00:00+00:00",
      "organization_id": "~{\"classification\": \"lower\"}",
      "classification": [
        "passage"
      ],
      "related_entities": [],
      "_processing": {
        "log_file_created": "2025-10-24T23:24:27Z"
      }
    },
    {
      "description": "enrolled, signed by President of the Senate",
      "date": "2025-03-14T04:00:00+00:00",
      "organization_id": "~{\"classification\": \"upper\"}",
      "classification": [
        "passage"
      ],
      "related_entities": [],
      "_processing": {
        "log_file_created": "2025-10-24T23:24:27Z"
      }
    },
    {
      "description": "delivered to Governor",
      "date": "2025-03-14T04:00:00+00:00",
      "organization_id": "~{\"classification\": \"lower\"}",
      "classification": [],
      "related_entities": [],
      "_processing": {
        "log_file_created": "2025-10-24T23:24:27Z"
      }
    },
    {
      "description": "line items vetoed",
      "date": "2025-03-25T04:00:00+00:00",
      "organization_id": "~{\"classification\": \"lower\"}",
      "classification": [
        "executive-veto-line-item"
      ],
      "related_entities": [],
      "_processing": {
        "log_file_created": "2025-10-24T23:24:27Z"
      }
    },
    {
      "description": "received in House",
      "date": "2025-03-27T04:00:00+00:00",
      "organization_id": "~{\"classification\": \"lower\"}",
      "classification": [],
      "related_entities": [],
      "_processing": {
        "log_file_created": "2025-10-24T23:24:27Z"
      }
    },
    {
      "description": "to Rules (H)",
      "date": "2025-03-27T04:00:00+00:00",
      "organization_id": "~{\"classification\": \"lower\"}",
      "classification": [
        "referral-committee"
      ],
      "related_entities": [],
      "_processing": {
        "log_file_created": "2025-10-24T23:24:27Z"
      }
    },
    {
      "description": "taken from Rules",
      "date": "2025-03-27T04:00:00+00:00",
      "organization_id": "~{\"classification\": \"lower\"}",
      "classification": [],
      "related_entities": [],
      "_processing": {
        "log_file_created": "2025-10-24T23:24:27Z"
      }
    },
    {
      "description": "posted for consideration of Governor's veto",
      "date": "2025-03-27T04:00:00+00:00",
      "organization_id": "~{\"classification\": \"lower\"}",
      "classification": [],
      "related_entities": [],
      "_processing": {
        "log_file_created": "2025-10-24T23:24:27Z"
      }
    },
    {
      "description": "veto overridden",
      "date": "2025-03-27T04:00:00+00:00",
      "organization_id": "~{\"classification\": \"lower\"}",
      "classification": [
        "veto-override-passage"
      ],
      "related_entities": [],
      "_processing": {
        "log_file_created": "2025-10-24T23:24:27Z"
      }
    },
    {
      "description": "passed 77-16",
      "date": "2025-03-27T04:00:00+00:00",
      "organization_id": "~{\"classification\": \"lower\"}",
      "classification": [
        "passage"
      ],
      "related_entities": [],
      "_processing": {
        "log_file_created": "2025-10-24T23:24:27Z"
      }
    },
    {
      "description": "received in Senate",
      "date": "2025-03-27T04:00:00+00:00",
      "organization_id": "~{\"classification\": \"upper\"}",
      "classification": [],
      "related_entities": [],
      "_processing": {
        "log_file_created": "2025-10-24T23:24:27Z"
      }
    },
    {
      "description": "to Rules (S)",
      "date": "2025-03-27T04:00:00+00:00",
      "organization_id": "~{\"classification\": \"upper\"}",
      "classification": [
        "referral-committee"
      ],
      "related_entities": [],
      "_processing": {
        "log_file_created": "2025-10-24T23:24:27Z"
      }
    },
    {
      "description": "posted for passage for consideration of Governor's veto",
      "date": "2025-03-27T04:00:00+00:00",
      "organization_id": "~{\"classification\": \"lower\"}",
      "classification": [],
      "related_entities": [],
      "_processing": {
        "log_file_created": "2025-10-24T23:24:27Z"
      }
    },
    {
      "description": "veto overridden",
      "date": "2025-03-27T04:00:00+00:00",
      "organization_id": "~{\"classification\": \"lower\"}",
      "classification": [
        "veto-override-passage"
      ],
      "related_entities": [],
      "_processing": {
        "log_file_created": "2025-10-24T23:24:27Z"
      }
    },
    {
      "description": "passed 32-6",
      "date": "2025-03-27T04:00:00+00:00",
      "organization_id": "~{\"classification\": \"lower\"}",
      "classification": [
        "passage"
      ],
      "related_entities": [],
      "_processing": {
        "log_file_created": "2025-10-24T23:24:27Z"
      }
    },
    {
      "description": "received in House",
      "date": "2025-03-27T04:00:00+00:00",
      "organization_id": "~{\"classification\": \"lower\"}",
      "classification": [],
      "related_entities": [],
      "_processing": {
        "log_file_created": "2025-10-24T23:24:27Z"
      }
    },
    {
      "description": "enrolled, signed by Speaker of the House",
      "date": "2025-03-27T04:00:00+00:00",
      "organization_id": "~{\"classification\": \"lower\"}",
      "classification": [
        "passage"
      ],
      "related_entities": [],
      "_processing": {
        "log_file_created": "2025-10-24T23:24:27Z"
      }
    },
    {
      "description": "enrolled, signed by President of the Senate",
      "date": "2025-03-27T04:00:00+00:00",
      "organization_id": "~{\"classification\": \"upper\"}",
      "classification": [
        "passage"
      ],
      "related_entities": [],
      "_processing": {
        "log_file_created": "2025-10-24T23:24:27Z"
      }
    },
    {
      "description": "delivered to Secretary of State (Acts Ch. 108)",
      "date": "2025-03-27T04:00:00+00:00",
      "organization_id": "~{\"classification\": \"lower\"}",
      "classification": [
        "became-law"
      ],
      "related_entities": [],
      "_processing": {
        "log_file_created": "2025-10-24T23:24:27Z"
      }
    }
  ],
  "sponsorships": [],
  "related_bills": [],
  "versions": [
    {
      "note": "Acts Chapter 108",
      "links": [
        {
          "url": "https://apps.legislature.ky.gov/law/acts/25RS/documents/0108.pdf",
          "media_type": "application/pdf"
        }
      ],
      "date": "",
      "classification": ""
    },
    {
      "note": "Current/Final",
      "links": [
        {
          "url": "https://apps.legislature.ky.gov/recorddocuments/bill/25RS/hb546/bill.pdf",
          "media_type": "application/pdf"
        }
      ],
      "date": "",
      "classification": ""
    },
    {
      "note": "Introduced",
      "links": [
        {
          "url": "https://apps.legislature.ky.gov/recorddocuments/bill/25RS/hb546/orig_bill.pdf",
          "media_type": "application/pdf"
        }
      ],
      "date": "",
      "classification": ""
    }
  ],
  "documents": [
    {
      "note": "Proposed House Committee Substitute 1",
      "links": [
        {
          "url": "https://apps.legislature.ky.gov/recorddocuments/bill/25RS/HB546/HCS1.pdf",
          "media_type": ""
        }
      ],
      "date": "",
      "classification": ""
    },
    {
      "note": "Proposed Senate Committee Substitute 1",
      "links": [
        {
          "url": "https://apps.legislature.ky.gov/recorddocuments/bill/25RS/HB546/SCS1.pdf",
          "media_type": ""
        }
      ],
      "date": "",
      "classification": ""
    },
    {
      "note": "Proposed Senate Committee Amendment 1",
      "links": [
        {
          "url": "https://apps.legislature.ky.gov/recorddocuments/bill/25RS/HB546/SCA1.pdf",
          "media_type": ""
        }
      ],
      "date": "",
      "classification": ""
    },
    {
      "note": "Proposed Conference Committee Report 1",
      "links": [
        {
          "url": "https://apps.legislature.ky.gov/recorddocuments/bill/25RS/HB546/CCR1.pdf",
          "media_type": ""
        }
      ],
      "date": "",
      "classification": ""
    },
    {
      "note": "Proposed Free Conference Committee Report 1",
      "links": [
        {
          "url": "https://apps.legislature.ky.gov/recorddocuments/bill/25RS/HB546/FCCR1.pdf",
          "media_type": ""
        }
      ],
      "date": "",
      "classification": ""
    }
  ],
  "citations": [],
  "sources": [
    {
      "url": "https://apps.legislature.ky.gov/record/25RS/hb546.html",
      "note": ""
    }
  ],
  "extras": {
    "BDR": "1189"
  },
  "jurisdiction": {
    "id": "ocd-jurisdiction/country:us/state:ky/government",
    "name": "Kentucky",
    "classification": "state",
    "division_id": "ocd-division/country:us/state:ky"
  },
  "_processing": {
    "logs_latest_update": "2025-10-24T23:24:27Z",
    "text_extraction_latest_update": "2025-10-25T05:43:40.591727Z"
  }
}