{
  "legislative_session": "2025RS",
  "identifier": "HB708",
  "title": "AN ACT relating to small business.",
  "from_organization": "~{\"classification\": \"lower\"}",
  "classification": [
    "bill"
  ],
  "subject": [
    "Small Business",
    "Technical Corrections"
  ],
  "abstracts": [
    {
      "note": "Summary of Original Version",
      "abstract": "Amend KRS 154.12-330 to make technical corrections."
    }
  ],
  "other_titles": [],
  "other_identifiers": [],
  "actions": [
    {
      "description": "introduced in House",
      "date": "2025-02-19T05:00:00+00:00",
      "organization_id": "~{\"classification\": \"lower\"}",
      "classification": [
        "introduction"
      ],
      "related_entities": [],
      "_processing": {
        "log_file_created": "2025-10-24T23:24:27Z"
      }
    },
    {
      "description": "to Committee on Committees (H)",
      "date": "2025-02-19T05:00:00+00:00",
      "organization_id": "~{\"classification\": \"lower\"}",
      "classification": [
        "referral-committee"
      ],
      "related_entities": [],
      "_processing": {
        "log_file_created": "2025-10-24T23:24:27Z"
      }
    },
    {
      "description": "to Small Business & Information Technology (H)",
      "date": "2025-02-27T05:00:00+00:00",
      "organization_id": "~{\"classification\": \"lower\"}",
      "classification": [
        "referral-committee"
      ],
      "related_entities": [],
      "_processing": {
        "log_file_created": "2025-10-24T23:24:27Z"
      }
    }
  ],
  "sponsorships": [],
  "related_bills": [],
  "versions": [
    {
      "note": "Introduced",
      "links": [
        {
          "url": "https://apps.legislature.ky.gov/recorddocuments/bill/25RS/hb708/orig_bill.pdf",
          "media_type": "application/pdf"
        }
      ],
      "date": "",
      "classification": ""
    }
  ],
  "documents": [],
  "citations": [],
  "sources": [
    {
      "url": "https://apps.legislature.ky.gov/record/25RS/hb708.html",
      "note": ""
    }
  ],
  "extras": {
    "BDR": "1642"
  },
  "jurisdiction": {
    "id": "ocd-jurisdiction/country:us/state:ky/government",
    "name": "Kentucky",
    "classification": "state",
    "division_id": "ocd-division/country:us/state:ky"
  },
  "_processing": {
    "logs_latest_update": "2025-10-24T23:24:27Z",
    "text_extraction_latest_update": "2025-10-25T04:22:44.119578Z"
  }
}