{
  "legislative_session": "2025RS",
  "identifier": "HB410",
  "title": "AN ACT relating to prohibiting the possession and transfer of assault weapons and large capacity ammunition feeding devices.",
  "from_organization": "~{\"classification\": \"lower\"}",
  "classification": [
    "bill"
  ],
  "subject": [
    "Corrections Impact",
    "Crimes and Punishments",
    "Firearms and Weapons",
    "Local Mandate"
  ],
  "abstracts": [
    {
      "note": "Summary of Original Version",
      "abstract": "Amend KRS 527.010 to define \"assault weapon\" and \"large capacity ammunition feeding device\"; create new sections of KRS Chapter 527 to criminalize possession and transfer of large capacity ammunition feeding devices; criminalize the possession and transfer of assault weapons; provide exceptions for large capacity ammunition feeding devices and assault weapons lawfully owned prior to the effective date of this Act; amend KRS 237.104 to conform."
    }
  ],
  "other_titles": [],
  "other_identifiers": [],
  "actions": [
    {
      "description": "introduced in House",
      "date": "2025-02-07T05:00:00+00:00",
      "organization_id": "~{\"classification\": \"lower\"}",
      "classification": [
        "introduction"
      ],
      "related_entities": [],
      "_processing": {
        "log_file_created": "2025-10-24T23:24:26Z"
      }
    },
    {
      "description": "to Committee on Committees (H)",
      "date": "2025-02-07T05:00:00+00:00",
      "organization_id": "~{\"classification\": \"lower\"}",
      "classification": [
        "referral-committee"
      ],
      "related_entities": [],
      "_processing": {
        "log_file_created": "2025-10-24T23:24:26Z"
      }
    },
    {
      "description": "to Judiciary (H)",
      "date": "2025-02-12T05:00:00+00:00",
      "organization_id": "~{\"classification\": \"lower\"}",
      "classification": [
        "referral-committee"
      ],
      "related_entities": [],
      "_processing": {
        "log_file_created": "2025-10-24T23:24:26Z"
      }
    }
  ],
  "sponsorships": [],
  "related_bills": [],
  "versions": [
    {
      "note": "Introduced",
      "links": [
        {
          "url": "https://apps.legislature.ky.gov/recorddocuments/bill/25RS/hb410/orig_bill.pdf",
          "media_type": "application/pdf"
        }
      ],
      "date": "",
      "classification": ""
    }
  ],
  "documents": [
    {
      "note": "Fiscal Note",
      "links": [
        {
          "url": "https://apps.legislature.ky.gov/recorddocuments/note/25RS/hb410/LM.pdf",
          "media_type": "application/pdf"
        }
      ],
      "date": "",
      "classification": ""
    }
  ],
  "citations": [],
  "sources": [
    {
      "url": "https://apps.legislature.ky.gov/record/25RS/hb410.html",
      "note": ""
    }
  ],
  "extras": {
    "BDR": "1050"
  },
  "jurisdiction": {
    "id": "ocd-jurisdiction/country:us/state:ky/government",
    "name": "Kentucky",
    "classification": "state",
    "division_id": "ocd-division/country:us/state:ky"
  },
  "_processing": {
    "logs_latest_update": "2025-10-24T23:24:26Z"
  }
}