{
  "legislative_session": "2025RS",
  "identifier": "HB192",
  "title": "AN ACT relating to income taxation of military pensions.",
  "from_organization": "~{\"classification\": \"lower\"}",
  "classification": [
    "bill"
  ],
  "subject": [
    "Military Affairs and Civil Defense",
    "Reports Mandated",
    "Retirement and Pensions",
    "State Agencies",
    "Taxation",
    "Taxation, Income--Individual",
    "Veterans"
  ],
  "abstracts": [
    {
      "note": "Summary of Original Version",
      "abstract": "Amend KRS 141.019 to exclude all distributions from military pension plans received by retired members of the United States military and National Guard and their surviving spouse or former spouse under a survivor benefit plan from income taxation for taxable years beginning on or after January 1, 2026, but before January 1, 2030; require reporting by the Department of Revenue; amend KRS 131.190 to conform."
    }
  ],
  "other_titles": [],
  "other_identifiers": [],
  "actions": [
    {
      "description": "introduced in House",
      "date": "2025-01-09T05:00:00+00:00",
      "organization_id": "~{\"classification\": \"lower\"}",
      "classification": [
        "introduction"
      ],
      "related_entities": [],
      "_processing": {
        "log_file_created": "2025-10-24T23:24:27Z"
      }
    },
    {
      "description": "to Committee on Committees (H)",
      "date": "2025-01-09T05:00:00+00:00",
      "organization_id": "~{\"classification\": \"lower\"}",
      "classification": [
        "referral-committee"
      ],
      "related_entities": [],
      "_processing": {
        "log_file_created": "2025-10-24T23:24:27Z"
      }
    },
    {
      "description": "to Appropriations & Revenue (H)",
      "date": "2025-02-04T05:00:00+00:00",
      "organization_id": "~{\"classification\": \"lower\"}",
      "classification": [
        "referral-committee"
      ],
      "related_entities": [],
      "_processing": {
        "log_file_created": "2025-10-24T23:24:27Z"
      }
    }
  ],
  "sponsorships": [],
  "related_bills": [],
  "versions": [
    {
      "note": "Introduced",
      "links": [
        {
          "url": "https://apps.legislature.ky.gov/recorddocuments/bill/25RS/hb192/orig_bill.pdf",
          "media_type": "application/pdf"
        }
      ],
      "date": "",
      "classification": ""
    }
  ],
  "documents": [],
  "citations": [],
  "sources": [
    {
      "url": "https://apps.legislature.ky.gov/record/25RS/hb192.html",
      "note": ""
    }
  ],
  "extras": {
    "BDR": "282"
  },
  "jurisdiction": {
    "id": "ocd-jurisdiction/country:us/state:ky/government",
    "name": "Kentucky",
    "classification": "state",
    "division_id": "ocd-division/country:us/state:ky"
  },
  "_processing": {
    "logs_latest_update": "2025-10-24T23:24:27Z"
  }
}