{
  "legislative_session": "2025RS",
  "identifier": "HB577",
  "title": "AN ACT relating to planning and zoning.",
  "from_organization": "~{\"classification\": \"lower\"}",
  "classification": [
    "bill"
  ],
  "subject": [
    "Housing, Building, and Construction",
    "Land Use",
    "Local Government",
    "Local Mandate",
    "Planning and Zoning"
  ],
  "abstracts": [
    {
      "note": "Summary of Original Version",
      "abstract": "Create a new section KRS Chapter 100  to define terms; allow multi-unit dwellings and mixed-use developments as permitted uses in commercial zones; prohibit a planning unit from adopting or enforcing regulations that do not allow multi-unit dwellings and mixed-use developments in commercial zones, impose requirements on multi-unit dwellings or mixed-use developments more restrictive than other uses in a zone, or require certain parking restrictions on multi-unit dwellings or mixed-use developments."
    }
  ],
  "other_titles": [],
  "other_identifiers": [],
  "actions": [
    {
      "description": "introduced in House",
      "date": "2025-02-14T05:00:00+00:00",
      "organization_id": "~{\"classification\": \"lower\"}",
      "classification": [
        "introduction"
      ],
      "related_entities": [],
      "_processing": {
        "log_file_created": "2025-10-24T23:24:26Z"
      }
    },
    {
      "description": "to Committee on Committees (H)",
      "date": "2025-02-14T05:00:00+00:00",
      "organization_id": "~{\"classification\": \"lower\"}",
      "classification": [
        "referral-committee"
      ],
      "related_entities": [],
      "_processing": {
        "log_file_created": "2025-10-24T23:24:26Z"
      }
    },
    {
      "description": "to Local Government (H)",
      "date": "2025-02-25T05:00:00+00:00",
      "organization_id": "~{\"classification\": \"lower\"}",
      "classification": [
        "referral-committee"
      ],
      "related_entities": [],
      "_processing": {
        "log_file_created": "2025-10-24T23:24:26Z"
      }
    }
  ],
  "sponsorships": [],
  "related_bills": [],
  "versions": [
    {
      "note": "Introduced",
      "links": [
        {
          "url": "https://apps.legislature.ky.gov/recorddocuments/bill/25RS/hb577/orig_bill.pdf",
          "media_type": "application/pdf"
        }
      ],
      "date": "",
      "classification": ""
    }
  ],
  "documents": [
    {
      "note": "Fiscal Note",
      "links": [
        {
          "url": "https://apps.legislature.ky.gov/recorddocuments/note/25RS/hb577/LM.pdf",
          "media_type": "application/pdf"
        }
      ],
      "date": "",
      "classification": ""
    }
  ],
  "citations": [],
  "sources": [
    {
      "url": "https://apps.legislature.ky.gov/record/25RS/hb577.html",
      "note": ""
    }
  ],
  "extras": {
    "BDR": "1107"
  },
  "jurisdiction": {
    "id": "ocd-jurisdiction/country:us/state:ky/government",
    "name": "Kentucky",
    "classification": "state",
    "division_id": "ocd-division/country:us/state:ky"
  },
  "_processing": {
    "logs_latest_update": "2025-10-24T23:24:26Z"
  }
}