{
  "legislative_session": "2025RS",
  "identifier": "SB45",
  "title": "AN ACT relating to Kentucky educational excellence scholarships.",
  "from_organization": "~{\"classification\": \"upper\"}",
  "classification": [
    "bill"
  ],
  "subject": [
    "Education, Elementary and Secondary",
    "Education, Finance",
    "Education, Higher",
    "Effective Dates, Delayed"
  ],
  "abstracts": [
    {
      "note": "Summary of Original Version",
      "abstract": "Amend KRS 164.7879 to increase the Kentucky educational excellence scholarship base amount for each eligible grade point average; increase the supplemental award amounts; require a supplemental award for eligible Cambridge Advanced International scores; amend KRS 164.7882 to increase the award amount for an eligible student enrolled in a comprehensive transition and postsecondary program; amend KRS 164.7874, 164.7881, 164.7884, and 164.7885 to conform; EFFECTIVE July 1, 2025."
    }
  ],
  "other_titles": [],
  "other_identifiers": [],
  "actions": [
    {
      "description": "introduced in Senate",
      "date": "2025-01-07T05:00:00+00:00",
      "organization_id": "~{\"classification\": \"upper\"}",
      "classification": [
        "introduction"
      ],
      "related_entities": [],
      "_processing": {
        "log_file_created": "2025-10-24T23:24:26Z"
      }
    },
    {
      "description": "to Committee on Committees (S)",
      "date": "2025-01-07T05:00:00+00:00",
      "organization_id": "~{\"classification\": \"upper\"}",
      "classification": [
        "referral-committee"
      ],
      "related_entities": [],
      "_processing": {
        "log_file_created": "2025-10-24T23:24:26Z"
      }
    },
    {
      "description": "to Education (S)",
      "date": "2025-01-09T05:00:00+00:00",
      "organization_id": "~{\"classification\": \"upper\"}",
      "classification": [
        "referral-committee"
      ],
      "related_entities": [],
      "_processing": {
        "log_file_created": "2025-10-24T23:24:26Z"
      }
    }
  ],
  "sponsorships": [],
  "related_bills": [],
  "versions": [
    {
      "note": "Introduced",
      "links": [
        {
          "url": "https://apps.legislature.ky.gov/recorddocuments/bill/25RS/sb45/orig_bill.pdf",
          "media_type": "application/pdf"
        }
      ],
      "date": "",
      "classification": ""
    }
  ],
  "documents": [],
  "citations": [],
  "sources": [
    {
      "url": "https://apps.legislature.ky.gov/record/25RS/sb45.html",
      "note": ""
    }
  ],
  "extras": {
    "BDR": "161"
  },
  "jurisdiction": {
    "id": "ocd-jurisdiction/country:us/state:ky/government",
    "name": "Kentucky",
    "classification": "state",
    "division_id": "ocd-division/country:us/state:ky"
  },
  "_processing": {
    "logs_latest_update": "2025-10-24T23:24:26Z"
  }
}